lkbuild/__init__.py
lkbuild/__main__.py
lkbuild/datasets.py
lkbuild/env.py
lkbuild/tasks.py
lkbuild/data/__init__.py
lkbuild/data/ml-latest-small/README.txt
lkbuild/data/ml-latest-small/links.csv
lkbuild/data/ml-latest-small/movies.csv
lkbuild/data/ml-latest-small/ratings.csv
lkbuild/data/ml-latest-small/tags.csv
lkbuild/specs/mkl-spec.yml
lkbuild/specs/openblas-spec.yml
lkbuild/specs/python-3.10-spec.yml
lkbuild/specs/python-3.11-spec.yml
lkbuild/specs/python-3.7-spec.yml
lkbuild/specs/python-3.8-spec.yml
lkbuild/specs/python-3.9-spec.yml
lenskit_build_helpers-0.3.0.dist-info/entry_points.txt
lenskit_build_helpers-0.3.0.dist-info/LICENSE.md
lenskit_build_helpers-0.3.0.dist-info/WHEEL
lenskit_build_helpers-0.3.0.dist-info/METADATA
lenskit_build_helpers-0.3.0.dist-info/RECORD
