Metadata-Version: 2.1
Name: lenskit-build-helpers
Version: 0.3.0
Summary: LensKit build support helpers.
Author-email: Michael Ekstrand <michaelekstrand@boisestate.edu>
Requires-Python: >= 3.7
Requires-Dist: flit >=3.2,<4
Requires-Dist: requests ==2.*
Requires-Dist: invoke ==2.*
Requires-Dist: pip
Requires-Dist: conda-lock >=1.2.1
